duplicates/__init__.py
duplicates/duplicates.py
tests/__init__.py
tests/context.py
tests/test_detect_duplicates.py
Duplicate_Finder-1.4.0.dist-info/LICENSE
Duplicate_Finder-1.4.0.dist-info/METADATA
Duplicate_Finder-1.4.0.dist-info/WHEEL
Duplicate_Finder-1.4.0.dist-info/top_level.txt
Duplicate_Finder-1.4.0.dist-info/RECORD
