Metadata-Version: 2.1
Name: Duplicate-Finder
Version: 1.4.0
Summary: Package to find duplicate files in and across folders
Home-page: https://github.com/akcarsten/duplicates.git
Author: Carsten Klein
Author-email: 
License: MIT License
Platform: UNKNOWN
Classifier: Programming Language :: Python :: 3
Classifier: License :: OSI Approved :: MIT License
Classifier: Operating System :: OS Independent
Requires-Python: >=3.8
